Metadata-Version: 1.1
Name: lgame
Version: 0.0.4
Summary: game
Home-page: https://github.com/
Author: Yuanghang Zhang
Author-email: 1957298862@qq.com
License: UNKNOWN
Platform: UNKNOWN
Classifier: Programming Language :: Python :: 3
Classifier: License :: OSI Approved :: MIT License
Classifier: Operating System :: OS Independent
